sam_games/Rock_Paper_Scissor.py
sam_games/__init__.py
sam_games/sam_games.__main__.py
sam_games/snake.py
sam_games/tict_tack_toe.py
sam_games-0.0.10.dist-info/License.txt
sam_games-0.0.10.dist-info/METADATA
sam_games-0.0.10.dist-info/WHEEL
sam_games-0.0.10.dist-info/top_level.txt
sam_games-0.0.10.dist-info/RECORD
