Metadata-Version: 2.1
Name: sam-games
Version: 0.0.10
Summary: python based games using turtle
Author-email: Byri Neeraj S <byrineeraj@gmail.com>
Project-URL: Homepage, https://github.com/pypa/sampleproject
Project-URL: Bug Tracker, https://github.com/pypa/sampleproject/issues
Classifier: Programming Language :: Python :: 3
Classifier: License :: OSI Approved :: MIT License
Classifier: Operating System :: OS Independent
Requires-Python: >=3.7
License-File: License.txt
